{
  "program": [
    {
      "program_id": "10060101110201A",
      "project_id": "0",
      "major_id": "0",
      "program_name_th": "หลักสูตรวิทยาศาสตรบัณฑิต สาขาวิชากายอุปกรณ์",
      "program_type_name_th": "ภาษาไทย ปกติ",
      "major_name_th": "0",
      "project_name_th": "0",
      "min_score": 53.0338,
      "max_score": 59.3958,
      "min_score_ds": 52.6774,
      "max_score_ds": 59.3958,
      "receive_student_number": 15,
      "scores": {
        "tgat": 30,
        "a_lv_61": 14,
        "a_lv_64": 14,
        "a_lv_65": 14,
        "a_lv_66": 14,
        "a_lv_82": 14
      }
    }
  ],
  "rounds": [
    {
      "_id": "68ef2a0e64cc1de047883454",
      "university_id": "006",
      "program_id": "10060101110201A",
      "type": "1_2569",
      "receive_student_number": 12,
      "only_formal": 1,
      "only_international": 2,
      "only_vocational": 2,
      "only_non_formal": 2,
      "only_ged": 2,
      "description": "หลักสูตร 4 ปี",
      "condition": "รายละเอียดตามที่มหาวิทยาลัยกำหนดไว้ในประกาศ https://tcas.mahidol.ac.th และประกาศของคณะหลักสูตรที่เปิดรับ",
      "interview_location": "มหาวิทยาลัยมหิดล ถ.พุทธมณฑลสาย 4 ต.ศาลายา อ.พุทธมณฑล จ.นครปฐม 73170 กองบริหารการศึกษา อาคารศูนย์การเรียนรู้มหิดล MLC",
      "interview_date": "ตามกำหนดการของมหาวิทยาลัย https://tcas.mahidol.ac.th/",
      "link": "https://www2.si.mahidol.ac.th/sspo/",
      "grad_current": false,
      "t_score": false,
      "min_gpax": 3.5,
      "min_gpa22": 3,
      "min_gpa23": 3.25,
      "min_gpa28": 3.25,
      "score_conditions": {
        "min_gpax": 3.5,
        "min_gpa22": 3,
        "min_gpa23": 3.25,
        "min_gpa28": 3.25
      },
      "folio": {
        "closed_date": "0",
        "page_limit": "0"
      },
      "created_at": "2025-10-15T04:58:54.046Z"
    },
    {
      "_id": "68f6f8e127b76be0eb0876a1",
      "university_id": "006",
      "program_id": "10060101110201A",
      "project_id": "B2001",
      "project_name_th": "โครงการพิเศษ โครงการสายใยกายอุปกรณ์และวีรชนรั้วแห่งชาติไทย",
      "type": "2_2569",
      "receive_student_number": 2,
      "only_formal": 1,
      "only_international": 1,
      "only_vocational": 1,
      "only_non_formal": 1,
      "only_ged": 1,
      "description": "หลักสูตร 4 ปี",
      "condition": "รายละเอียดตามที่มหาวิทยาลัยกำหนดไว้ในประกาศ https://tcas.mahidol.ac.th และประกาศของคณะหลักสูตรที่เปิดรับ",
      "interview_location": "โรงเรียนกายอุปกรณ์สิรินธร คณะแพทยศาสตร์ศิริราชพยาบาล",
      "interview_date": "จะแจ้งภายหลัง",
      "interview_time": "จะแจ้งภายหลัง",
      "link": "https://drive.google.com/drive/folders/1RAWq75oyTA9wqrm5TGGpg1bYb3c_Z8of?usp=sharing",
      "grad_current": false,
      "t_score": false,
      "min_gpax": 3,
      "score_conditions": {
        "min_gpax": 3
      },
      "created_at": "2025-10-21T03:07:13.848Z"
    },
    {
      "_id": "68f6f8e227b76be0eb0877c1",
      "university_id": "006",
      "program_id": "10060101110201A",
      "type": "3_2569",
      "receive_student_number": 10,
      "only_formal": 1,
      "only_international": 1,
      "only_vocational": 1,
      "only_non_formal": 1,
      "only_ged": 1,
      "description": "หลักสูตร 4 ปี",
      "condition": "รายละเอียดตามที่มหาวิทยาลัยกำหนดไว้ในประกาศ https://tcas.mahidol.ac.th และประกาศของคณะหลักสูตรที่เปิดรับ",
      "interview_location": "โรงเรียนกายอุปกรณ์สิรินธร คณะแพทยศาสตร์ศิริราชพยาบาล",
      "interview_date": "จะแจ้งภายหลัง",
      "interview_time": "จะแจ้งภายหลัง",
      "link": "https://drive.google.com/drive/folders/1RAWq75oyTA9wqrm5TGGpg1bYb3c_Z8of?usp=sharing",
      "grad_current": false,
      "t_score": false,
      "score_conditions": {
        "min_tgat": 1,
        "min_a_lv_61": 1,
        "min_a_lv_64": 1,
        "min_a_lv_65": 1,
        "min_a_lv_66": 1,
        "min_a_lv_82": 35,
        "score_condition": 1,
        "subject_names": "min_a_lv_82",
        "score_minimum": "35"
      },
      "created_at": "2025-10-21T03:07:14.693Z",
      "min_total_score": 0,
      "scores": {
        "tgat": 30,
        "a_lv_61": 14,
        "a_lv_64": 14,
        "a_lv_65": 14,
        "a_lv_66": 14,
        "a_lv_82": 14
      }
    }
  ]
}