{
  "program": [
    {
      "program_id": "10200118211401A",
      "project_id": "N3001",
      "major_id": "0",
      "program_name_th": "หลักสูตรวิทยาศาสตรบัณฑิต สาขาเทคโนโลยีนวัตกรรมพลังงานและสิ่งแวดล้อม",
      "program_type_name_th": "ภาษาไทย ปกติ",
      "major_name_th": "0",
      "project_name_th": "admission (แบบที่ 1)",
      "min_score": 43.1098,
      "max_score": 51.3781,
      "min_score_ds": 41.3248,
      "max_score_ds": 51.3781,
      "receive_student_number": 30,
      "scores": {
        "gpax": 25,
        "tgat": 30,
        "a_lv_61": 15,
        "a_lv_64": 15,
        "a_lv_65": 10,
        "a_lv_66": 5
      }
    },
    {
      "program_id": "10200118211401A",
      "project_id": "N3002",
      "major_id": "0",
      "program_name_th": "หลักสูตรวิทยาศาสตรบัณฑิต สาขาเทคโนโลยีนวัตกรรมพลังงานและสิ่งแวดล้อม",
      "program_type_name_th": "ภาษาไทย ปกติ",
      "major_name_th": "0",
      "project_name_th": "admission (แบบที่ 2)",
      "min_score": 46.7314,
      "max_score": 54.8989,
      "min_score_ds": 46.3714,
      "max_score_ds": 52.6077,
      "receive_student_number": 20,
      "scores": {
        "gpax": 25,
        "tgat": 35,
        "a_lv_61": 20,
        "a_lv_63": 20
      }
    }
  ],
  "rounds": [
    {
      "_id": "68e37ed62ef4c36c489ab2d1",
      "university_id": "020",
      "program_id": "10200118211401A",
      "project_id": "N1002",
      "project_name_th": "โครงการเด็กดีมีที่เรียน (สำหรับโรงเรียนที่สังกัด สพม. สพฐ. เท่านั้น)",
      "type": "1_2569",
      "receive_student_number": 5,
      "only_formal": 1,
      "only_international": 2,
      "only_vocational": 2,
      "only_non_formal": 2,
      "only_ged": 2,
      "description": "หลักสูตรวิทยาศาสตรบัณฑิต สาขาเทคโนโลยีนวัตกรรมพลังงานและสิ่งแวดล้อม",
      "condition": "https://www.admission.nu.ac.th/undergrad2.php",
      "interview_location": "มหาวิทยาลัยนเรศวร 99 หมู่ 9 ต.ท่าโพธิ์ อ.เมือง จ.พิษณุโลก 65000",
      "interview_date": "https://www.admission.nu.ac.th/undergrad2.php",
      "interview_time": "https://www.admission.nu.ac.th/undergrad2.php",
      "link": "https://www.admission.nu.ac.th/undergrad2.php",
      "grad_current": true,
      "t_score": false,
      "min_gpax": 2.5,
      "min_credit_gpa22": 10,
      "min_credit_gpa23": 5,
      "score_conditions": {
        "min_gpax": 2.5
      },
      "folio": {
        "folio_q1": "เป็นนักเรียนกำลังศึกษาอยู่ในระดับชั้นมัธยมศึกษาปีที่ 6 ในเขตพื้นที่ 18 จังหวัดได้แก่ จังหวัดเชียงราย เชียงใหม่ แม่ฮ่องสอน ลำพูน ลำปาง พะเยา น่าน แพร่ แพงเพชร ตาก นครสวรรค์ พิจิตร พิษณุโลก เพชรบูรณ์ สุโขทัย อุตรดิตถ์ อุทัยธานี ชัยนาท หรือไม่",
        "folio_q1_type": "A",
        "folio_q2": "โรงเรียนสังกัดสำนักงานคณะกรรมการการศึกษาขั้นพื้นฐานหรือไม่",
        "folio_q2_type": "A",
        "folio_q3": "มีผลงานด้านกิจกรรมอะไรบ้าง",
        "folio_q3_type": "C",
        "closed_date": "20/11/2568",
        "page_limit": "15"
      },
      "created_at": "2025-10-06T08:33:26.518Z",
      "min_total_score": 0,
      "scores": {
        "portfolio": 100
      }
    },
    {
      "_id": "68e37ed62ef4c36c489ab2d3",
      "university_id": "020",
      "program_id": "10200118211401A",
      "project_id": "N1003",
      "project_name_th": "โครงการเด็กดีมีที่เรียน (สำหรับโรงเรียนที่ไม่ได้สังกัด สพม. สพฐ.)",
      "type": "1_2569",
      "receive_student_number": 5,
      "only_formal": 1,
      "only_international": 2,
      "only_vocational": 2,
      "only_non_formal": 2,
      "only_ged": 2,
      "description": "หลักสูตรวิทยาศาสตรบัณฑิต สาขาเทคโนโลยีนวัตกรรมพลังงานและสิ่งแวดล้อม",
      "condition": "https://www.admission.nu.ac.th/undergrad2.php",
      "interview_location": "มหาวิทยาลัยนเรศวร 99 หมู่ 9 ต.ท่าโพธิ์ อ.เมือง จ.พิษณุโลก 65000",
      "interview_date": "https://www.admission.nu.ac.th/undergrad2.php",
      "interview_time": "https://www.admission.nu.ac.th/undergrad2.php",
      "link": "https://www.admission.nu.ac.th/undergrad2.php",
      "grad_current": true,
      "t_score": false,
      "min_gpax": 2.5,
      "min_credit_gpa22": 10,
      "min_credit_gpa23": 5,
      "score_conditions": {
        "min_gpax": 2.5
      },
      "folio": {
        "folio_q1": "เป็นนักเรียนกำลังศึกษาอยู่ในระดับชั้นมัธยมศึกษาปีที่ 6 ในเขตพื้นที่ 18 จังหวัดได้แก่ จังหวัดเชียงราย เชียงใหม่ แม่ฮ่องสอน ลำพูน ลำปาง พะเยา น่าน แพร่ แพงเพชร ตาก นครสวรรค์ พิจิตร พิษณุโลก เพชรบูรณ์ สุโขทัย อุตรดิตถ์ อุทัยธานี ชัยนาท หรือไม่",
        "folio_q1_type": "A",
        "folio_q2": "โรงเรียนไม่ได้สังกัดสำนักงานคณะกรรมการการศึกษาขั้นพื้นฐานหรือไม่",
        "folio_q2_type": "A",
        "folio_q3": "มีผลงานด้านกิจกรรมอะไรบ้าง",
        "folio_q3_type": "C",
        "closed_date": "20/11/2568",
        "page_limit": "15"
      },
      "created_at": "2025-10-06T08:33:26.523Z",
      "min_total_score": 0,
      "scores": {
        "portfolio": 100
      }
    },
    {
      "_id": "68e37ed62ef4c36c489ab2d5",
      "university_id": "020",
      "program_id": "10200118211401A",
      "project_id": "N1004",
      "project_name_th": "โครงการผู้มีความสามารถพิเศษทางด้านกีฬา",
      "type": "1_2569",
      "receive_student_number": 2,
      "only_formal": 1,
      "only_international": 2,
      "only_vocational": 2,
      "only_non_formal": 2,
      "only_ged": 2,
      "description": "หลักสูตรวิทยาศาสตรบัณฑิต สาขาเทคโนโลยีนวัตกรรมพลังงานและสิ่งแวดล้อม",
      "condition": "https://www.admission.nu.ac.th/undergrad2.php",
      "interview_location": "มหาวิทยาลัยนเรศวร 99 หมู่ 9 ต.ท่าโพธิ์ อ.เมือง จ.พิษณุโลก 65000",
      "interview_date": "https://www.admission.nu.ac.th/undergrad2.php",
      "interview_time": "https://www.admission.nu.ac.th/undergrad2.php",
      "link": "https://www.admission.nu.ac.th/undergrad2.php",
      "grad_current": true,
      "t_score": false,
      "folio": {
        "folio_q1": "เคยเข้าร่วมแข่งขันในระดับต่างๆเหล่านี้อย่างใดอย่างหนึ่งหรือไม่ เช่น นักกีฬาตัวแทนทีมชาติไทยทุกระดับการแข่งขัน, เป็นนักกีฬาที่เข้าร่วมการแข่งขันการแข่งขันกีฬาไทยแลนด์โอเพ่น, กีฬาระดับนานาชาติ, กีฬาแห่งชาติ, กีฬาอาชีพ, กีฬาชิงชนะเลิศแห่งประเทศไทย, กีฬาเยาวชนแห่งชาติ, รายการแข่งขันกีฬาชิงถ้วยพระราชทานฯ หรือรางวัลพระราชทานฯ, กีฬาระดับสโมสร, กีฬานักเรียนนักศึกษาแห่งประเทศไทย, กีฬานักเรียนโรงเรียนกีฬาแห่งประเทศไทย, หรือเข้าร่วมการแข่งขันกีฬาที่สมาคมกีฬาแห่งประเทศไทยเป็นผู้จัดการแข่งขันระดับประเทศไทยขึ้นไป, การแข่งขันที่จัดขึ้นโดยภาครัฐหรือเอกชน ในระดับประเทศไทยขึ้นไป และทุกรายการแข่งขันต้องมีผลงานจากการแข่งขันได้อันดับที่ 1 - 3 ในรอบมหกรรมหรือรอบชิงชนะเลิศ ภายในระยะเวลาย้อนหลัง     ไม่เกิน 3 ปี (นับหลังจากวันที่เปิดรับสมัคร) และอนุโลมกรณีผลงานการแข่งขันในระดับภูมิภาค อันดับที่ 1 - 3 ย้อนหลังไม่เกิน 3 ปี",
        "folio_q1_type": "A",
        "folio_q2": "มีผลงานด้านกิจกรรมอะไรบ้าง",
        "folio_q2_type": "C",
        "closed_date": "20/11/2568",
        "page_limit": "15"
      },
      "created_at": "2025-10-06T08:33:26.528Z",
      "min_total_score": 0,
      "scores": {
        "portfolio": 100
      },
      "score_conditions": {}
    },
    {
      "_id": "68e37ed62ef4c36c489ab2d7",
      "university_id": "020",
      "program_id": "10200118211401A",
      "project_id": "N1005",
      "project_name_th": "โครงการผู้ที่มีความสามารถพิเศษทางด้านศิลปวัฒนธรรม (โครงการลูกพระฆเนศ)",
      "type": "1_2569",
      "receive_student_number": 2,
      "only_formal": 1,
      "only_international": 2,
      "only_vocational": 2,
      "only_non_formal": 2,
      "only_ged": 2,
      "description": "หลักสูตรวิทยาศาสตรบัณฑิต สาขาเทคโนโลยีนวัตกรรมพลังงานและสิ่งแวดล้อม",
      "condition": "https://www.admission.nu.ac.th/undergrad2.php",
      "interview_location": "มหาวิทยาลัยนเรศวร 99 หมู่ 9 ต.ท่าโพธิ์ อ.เมือง จ.พิษณุโลก 65000",
      "interview_date": "https://www.admission.nu.ac.th/undergrad2.php",
      "interview_time": "https://www.admission.nu.ac.th/undergrad2.php",
      "link": "https://www.admission.nu.ac.th/undergrad2.php",
      "grad_current": true,
      "t_score": false,
      "folio": {
        "folio_q1": "ผู้สมัครต้องมีความสามารถพิเศษอย่างใดอย่างหนึ่งดังต่อไปนี้หรือไม่ ความสามารถด้านดนตรี ประเภท เครื่องสาย เครื่องตี เครื่องเป่า ดนตรีพื้นบ้าน และสามารถอ่านโน้ตดนตรีสากลได้ หรือ ความสามารถด้านขับร้อง ประเภท เพลงไทยลูกทุ่ง ลูกกรุง ลูกทุ่งหมอลำ เพลงพื้นบ้าน หรือ ความสามารถด้านการเต้น ประเภท สามารถเต้นในรูปแบบแดนเซอร์วงดนตรีลูกทุ่ง , Contemporary Dance , Modern Dance , Cover Dance ได้อย่างดีมาก",
        "folio_q1_type": "A",
        "folio_q2": "มีผลงานด้านกิจกรรมอะไรบ้าง",
        "folio_q2_type": "C",
        "closed_date": "20/11/2568",
        "page_limit": "15"
      },
      "created_at": "2025-10-06T08:33:26.534Z",
      "min_total_score": 0,
      "scores": {
        "portfolio": 100
      },
      "score_conditions": {}
    },
    {
      "_id": "68e37ed62ef4c36c489ab2d9",
      "university_id": "020",
      "program_id": "10200118211401A",
      "project_id": "N1022",
      "project_name_th": "โควตาพิเศษสำหรับนักเรียนโรงเรียนมัธยมสาธิตมหาวิทยาลัยนเรศวร",
      "type": "1_2569",
      "receive_student_number": 5,
      "only_formal": 1,
      "only_international": 2,
      "only_vocational": 2,
      "only_non_formal": 2,
      "only_ged": 2,
      "description": "หลักสูตรวิทยาศาสตรบัณฑิต สาขาเทคโนโลยีนวัตกรรมพลังงานและสิ่งแวดล้อม",
      "condition": "https://www.admission.nu.ac.th/undergrad2.php",
      "interview_location": "มหาวิทยาลัยนเรศวร 99 หมู่ 9 ต.ท่าโพธิ์ อ.เมือง จ.พิษณุโลก 65000",
      "interview_date": "https://www.admission.nu.ac.th/undergrad2.php",
      "interview_time": "https://www.admission.nu.ac.th/undergrad2.php",
      "link": "https://www.admission.nu.ac.th/undergrad2.php",
      "grad_current": true,
      "t_score": false,
      "min_gpax": 2.5,
      "min_credit_gpa22": 10,
      "min_credit_gpa23": 5,
      "score_conditions": {
        "min_gpax": 2.5
      },
      "folio": {
        "folio_q1": "กำลังศึกษาระดับชั้นมัธยมศึกษาปีที่ 6 โรงเรียนมัธยมสาธิตมหาวิทยาลัยนเรศวร หรือไม่",
        "folio_q1_type": "A",
        "folio_q2": "มีผลงานด้านกิจกรรมอะไรบ้าง",
        "folio_q2_type": "C",
        "closed_date": "20/11/2568",
        "page_limit": "15"
      },
      "created_at": "2025-10-06T08:33:26.539Z",
      "min_total_score": 0,
      "scores": {
        "portfolio": 100
      }
    },
    {
      "_id": "68e37ed62ef4c36c489ab2db",
      "university_id": "020",
      "program_id": "10200118211401A",
      "project_id": "N1028",
      "project_name_th": "โครงการส่งเสริมนักนวัตกรรมทางด้านวิทยาศาสตร์จากการประกวดโครงงานวิทยาศาสตร์",
      "type": "1_2569",
      "receive_student_number": 5,
      "only_formal": 1,
      "only_international": 2,
      "only_vocational": 2,
      "only_non_formal": 2,
      "only_ged": 2,
      "description": "หลักสูตรวิทยาศาสตรบัณฑิต สาขาเทคโนโลยีนวัตกรรมพลังงานและสิ่งแวดล้อม",
      "condition": "https://www.admission.nu.ac.th/undergrad2.php",
      "interview_location": "มหาวิทยาลัยนเรศวร 99 หมู่ 9 ต.ท่าโพธิ์ อ.เมือง จ.พิษณุโลก 65000",
      "interview_date": "https://www.admission.nu.ac.th/undergrad2.php",
      "interview_time": "https://www.admission.nu.ac.th/undergrad2.php",
      "link": "https://www.admission.nu.ac.th/undergrad2.php",
      "grad_current": true,
      "t_score": false,
      "min_gpax": 2.5,
      "min_credit_gpa22": 10,
      "min_credit_gpa23": 5,
      "score_conditions": {
        "min_gpax": 2.5
      },
      "folio": {
        "folio_q1": "มีผลงานประกวดโครงงานวิทยาศาสตร์/เทคโนโลยี/สิ่งประดิษฐ์ หรือโครงการที่เกี่ยวข้องหรือไม่",
        "folio_q1_type": "A",
        "folio_q2": "มีผลงานด้านกิจกรรมอะไรบ้าง",
        "folio_q2_type": "C",
        "closed_date": "20/11/2568",
        "page_limit": "15"
      },
      "created_at": "2025-10-06T08:33:26.545Z",
      "min_total_score": 0,
      "scores": {
        "portfolio": 100
      }
    },
    {
      "_id": "68e37ed62ef4c36c489ab2dd",
      "university_id": "020",
      "program_id": "10200118211401A",
      "project_id": "N1029",
      "project_name_th": "โครงการส่งเสริมการศึกษาระดับอาชีวศึกษาสู่อุดมศึกษา",
      "type": "1_2569",
      "receive_student_number": 2,
      "only_formal": 2,
      "only_international": 2,
      "only_vocational": 1,
      "only_non_formal": 2,
      "only_ged": 2,
      "description": "หลักสูตรวิทยาศาสตรบัณฑิต สาขาเทคโนโลยีนวัตกรรมพลังงานและสิ่งแวดล้อม",
      "condition": "https://www.admission.nu.ac.th/undergrad2.php",
      "interview_location": "มหาวิทยาลัยนเรศวร 99 หมู่ 9 ต.ท่าโพธิ์ อ.เมือง จ.พิษณุโลก 65000",
      "interview_date": "https://www.admission.nu.ac.th/undergrad2.php",
      "interview_time": "https://www.admission.nu.ac.th/undergrad2.php",
      "link": "https://www.admission.nu.ac.th/undergrad2.php",
      "grad_current": true,
      "t_score": false,
      "folio": {
        "folio_q1": "เป็นนักศึกษาที่สำเร็จการศึกษาระดับประกาศนียบัตรวิชาชีพ (ปวช.) หรือเป็นนักศึกษาที่กำลังศึกษาอยู่ในชั้นประกาศนียบัตรวิชาชีพ (ปวช.3 ภาคปลาย) ในประเภทวิชาอุตสาหกรรม สาขาเครื่องกล เครื่องมือกลและซ่อมบำรุง ไฟฟ้าอิเล็กทรอนิกส์ ช่างยนต์ ช่างกลโรงงาน โยธา หรือ สาขาที่เกี่ยวข้องและ มีผลงานประกวดโครงงานวิทยาศาสตร์/เทคโนโลยี/สิ่งประดิษฐ์ หรือโครงการที่เกี่ยวข้องหรือไม่",
        "folio_q1_type": "A",
        "folio_q2": "มีผลงานด้านกิจกรรมอะไรบ้าง",
        "folio_q2_type": "C",
        "closed_date": "20/11/2568",
        "page_limit": "15"
      },
      "created_at": "2025-10-06T08:33:26.552Z",
      "min_total_score": 0,
      "scores": {
        "portfolio": 100
      },
      "score_conditions": {}
    },
    {
      "_id": "68e37ed62ef4c36c489ab2df",
      "university_id": "020",
      "program_id": "10200118211401A",
      "project_id": "N1031",
      "project_name_th": "โครงการรับตรงโดยคณะ/วิทยาลัย",
      "type": "1_2569",
      "receive_student_number": 20,
      "only_formal": 1,
      "only_international": 2,
      "only_vocational": 2,
      "only_non_formal": 2,
      "only_ged": 2,
      "description": "หลักสูตรวิทยาศาสตรบัณฑิต สาขาเทคโนโลยีนวัตกรรมพลังงานและสิ่งแวดล้อม",
      "condition": "https://www.admission.nu.ac.th/undergrad2.php",
      "interview_location": "มหาวิทยาลัยนเรศวร 99 หมู่ 9 ต.ท่าโพธิ์ อ.เมือง จ.พิษณุโลก 65000",
      "interview_date": "https://www.admission.nu.ac.th/undergrad2.php",
      "interview_time": "https://www.admission.nu.ac.th/undergrad2.php",
      "link": "https://www.admission.nu.ac.th/undergrad2.php",
      "grad_current": true,
      "t_score": false,
      "folio": {
        "folio_q1": "มีผลงานด้านกิจกรรมอะไรบ้าง",
        "folio_q1_type": "C",
        "closed_date": "20/11/2568",
        "page_limit": "15"
      },
      "created_at": "2025-10-06T08:33:26.556Z",
      "min_total_score": 0,
      "scores": {
        "portfolio": 100
      },
      "score_conditions": {}
    },
    {
      "_id": "68e37ed62ef4c36c489ab2e1",
      "university_id": "020",
      "program_id": "10200118211401A",
      "project_id": "N1034",
      "project_name_th": "โครงการลูกเกษตรเพื่อพัฒนาชุมชนยั่งยืน",
      "type": "1_2569",
      "receive_student_number": 2,
      "only_formal": 1,
      "only_international": 2,
      "only_vocational": 2,
      "only_non_formal": 2,
      "only_ged": 2,
      "description": "หลักสูตรวิทยาศาสตรบัณฑิต สาขาเทคโนโลยีนวัตกรรมพลังงานและสิ่งแวดล้อม",
      "condition": "https://www.admission.nu.ac.th/undergrad2.php",
      "interview_location": "มหาวิทยาลัยนเรศวร 99 หมู่ 9 ต.ท่าโพธิ์ อ.เมือง จ.พิษณุโลก 65000",
      "interview_date": "https://www.admission.nu.ac.th/undergrad2.php",
      "interview_time": "https://www.admission.nu.ac.th/undergrad2.php",
      "link": "https://www.admission.nu.ac.th/undergrad2.php",
      "grad_current": true,
      "t_score": false,
      "min_gpax": 2.5,
      "min_credit_gpa22": 10,
      "min_credit_gpa23": 5,
      "score_conditions": {
        "min_gpax": 2.5
      },
      "folio": {
        "folio_q1": "เป็นนักเรียนที่กำลังศึกษาหรือสำเร็จ ระดับชั้นมัธยมศึกษาตอนปลาย ระดับประกาศนียบัตรวิชาชีพ (ปวช.) ระดับประกาศนียบัตรวิชาชีพชั้นสูง (ปวส.) และระดับอนุปริญญา หรือเทียบเท่า สาขาช่างอุตสาหกรรม หรือสาขาที่เกี่ยวข้องและ เป็นนักเรียนที่เป็นบุตร/หลานเกษตรกร จะต้องเป็นบุตร/หลาย ของบิดา มาตรดา ปู่ ย่า ตา ยาย ที่สืบสายโลหิตโดยตรง หรือผู้ปกครอง (ในกรณีบิดา-มารดา เสียชีวิต) ที่มีอาชีพเกี่ยวข้องกับการเกษตร โดยจะต้องมีหนังสือรับรองจากผู้ใหญ่บ้าน กำนัน ซึ่งดูแลพื้นที่ที่ทำการเกษตรดังกล่าว และสำเนาบัตรเกษตรกร หรือบัญชีเกษตร ของบิดา มารดา ปู่ ย่า ตา ยาย หรือผู้ปกครอง (ถ้ามี) หรือ เป็นนักเรียนที่เป็นสมาชิกยุวเกษตร สำหรับสมาชิกยุวเกษตรกร จะต้องเป็นผู้ที่เข้าร่วมกลุ่มยุวเกษตรกรของทางโรงเรียน และได้เข้าร่วมกิจกรรมต่างๆ ที่ทางหน่วยงานที่เกี่ยวข้องจัดขึ้น มีเอกสารรับรองจากอาจารย์ที่ปรึกษา หรือผู้อำนวยการสถานศึกษา หรือ เป็นนักเรียนที่เข้าร่วมประกวดโครงการวิทยาศาสตร์การเกษตร จะต้องเป็นนักเรียนที่เคยเข้าร่วมการประกวดโครงการด้านวิทยาศาสตร์การเกษตร หรือโครงการเกี่ยวกับกับการเกษตร ในงานวิชาการที่มหาวิทยาลัยนเรศวรจัดขึ้น เช่นงานสัปดาห์วิทยาศาสตร์ งานเกษตรนเรศวรหรือไม่",
        "folio_q1_type": "A",
        "folio_q2": "มีผลงานด้านกิจกรรมอะไรบ้าง",
        "folio_q2_type": "C",
        "closed_date": "20/11/2568",
        "page_limit": "15"
      },
      "created_at": "2025-10-06T08:33:26.562Z",
      "min_total_score": 0,
      "scores": {
        "portfolio": 100
      }
    },
    {
      "_id": "68e37ed62ef4c36c489ab2e3",
      "university_id": "020",
      "program_id": "10200118211401A",
      "project_id": "N2001",
      "project_name_th": "โควตา",
      "type": "2_2569",
      "receive_student_number": 70,
      "only_formal": 1,
      "only_international": 2,
      "only_vocational": 2,
      "only_non_formal": 2,
      "only_ged": 2,
      "description": "หลักสูตรวิทยาศาสตรบัณฑิต สาขาเทคโนโลยีนวัตกรรมพลังงานและสิ่งแวดล้อม",
      "condition": "https://www.admission.nu.ac.th/undergrad2.php",
      "interview_location": "มหาวิทยาลัยนเรศวร 99 หมู่ 9 ต.ท่าโพธิ์ อ.เมือง จ.พิษณุโลก 65000",
      "interview_date": "https://www.admission.nu.ac.th/undergrad2.php",
      "interview_time": "https://www.admission.nu.ac.th/undergrad2.php",
      "link": "https://www.admission.nu.ac.th/undergrad2.php",
      "grad_current": true,
      "t_score": false,
      "min_gpax": 2.5,
      "min_credit_gpa22": 10,
      "min_credit_gpa23": 5,
      "score_conditions": {
        "min_gpax": 2.5
      },
      "created_at": "2025-10-06T08:33:26.568Z"
    },
    {
      "_id": "68e37ed62ef4c36c489ab2e5",
      "university_id": "020",
      "program_id": "10200118211401A",
      "project_id": "N3001",
      "project_name_th": "admission (แบบที่ 1)",
      "type": "3_2569",
      "receive_student_number": 40,
      "only_formal": 1,
      "only_international": 1,
      "only_vocational": 1,
      "only_non_formal": 1,
      "only_ged": 1,
      "description": "หลักสูตรวิทยาศาสตรบัณฑิต สาขาเทคโนโลยีนวัตกรรมพลังงานและสิ่งแวดล้อม",
      "condition": "https://www.admission.nu.ac.th/undergrad2.php",
      "interview_location": "มหาวิทยาลัยนเรศวร 99 หมู่ 9 ต.ท่าโพธิ์ อ.เมือง จ.พิษณุโลก 65000",
      "interview_date": "https://www.admission.nu.ac.th/undergrad2.php",
      "interview_time": "https://www.admission.nu.ac.th/undergrad2.php",
      "link": "https://www.admission.nu.ac.th/undergrad2.php",
      "grad_current": false,
      "t_score": false,
      "min_gpax": 2.25,
      "score_conditions": {
        "min_gpax": 2.25
      },
      "created_at": "2025-10-06T08:33:26.573Z",
      "min_total_score": 0,
      "scores": {
        "gpax": 25,
        "tgat": 30,
        "a_lv_61": 15,
        "a_lv_64": 15,
        "a_lv_65": 10,
        "a_lv_66": 5
      }
    },
    {
      "_id": "68e37ed62ef4c36c489ab2e7",
      "university_id": "020",
      "program_id": "10200118211401A",
      "project_id": "N3002",
      "project_name_th": "admission (แบบที่ 2)",
      "type": "3_2569",
      "receive_student_number": 30,
      "only_formal": 1,
      "only_international": 2,
      "only_vocational": 2,
      "only_non_formal": 2,
      "only_ged": 2,
      "description": "หลักสูตรวิทยาศาสตรบัณฑิต สาขาเทคโนโลยีนวัตกรรมพลังงานและสิ่งแวดล้อม",
      "condition": "https://www.admission.nu.ac.th/undergrad2.php",
      "interview_location": "มหาวิทยาลัยนเรศวร 99 หมู่ 9 ต.ท่าโพธิ์ อ.เมือง จ.พิษณุโลก 65000",
      "interview_date": "https://www.admission.nu.ac.th/undergrad2.php",
      "interview_time": "https://www.admission.nu.ac.th/undergrad2.php",
      "link": "https://www.admission.nu.ac.th/undergrad2.php",
      "grad_current": false,
      "t_score": false,
      "min_gpax": 2.25,
      "min_credit_gpa22": 10,
      "min_credit_gpa23": 5,
      "score_conditions": {
        "min_gpax": 2.25
      },
      "created_at": "2025-10-06T08:33:26.579Z",
      "min_total_score": 0,
      "scores": {
        "gpax": 25,
        "tgat": 35,
        "a_lv_61": 20,
        "a_lv_63": 20
      }
    }
  ]
}