{
  "program": [
    {
      "program_id": "10040119903201A",
      "project_id": "M3152",
      "major_id": "0",
      "program_name_th": "ร.บ.การเมืองและการปกครอง",
      "program_type_name_th": "ภาษาไทย ปกติ",
      "major_name_th": "0",
      "project_name_th": "การรับตรงร่วมกัน (รหัส 00431901301010-การเมืองและการปกครอง)",
      "min_score": 60.2761,
      "max_score": 63.9102,
      "min_score_ds": 59.6403,
      "max_score_ds": 63.9102,
      "receive_student_number": 13,
      "scores": {
        "gpax": 10,
        "tgat": 30,
        "a_lv_61": 15,
        "a_lv_70": 15,
        "a_lv_81": 15,
        "a_lv_82": 15
      }
    },
    {
      "program_id": "10040119903201A",
      "project_id": "M3153",
      "major_id": "0",
      "program_name_th": "ร.บ.การเมืองและการปกครอง",
      "program_type_name_th": "ภาษาไทย ปกติ",
      "major_name_th": "0",
      "project_name_th": "การรับตรงร่วมกัน (รหัส 00431901301020-การเมืองและการปกครอง)",
      "min_score": 61.9774,
      "max_score": 63.8439,
      "min_score_ds": 61.7449,
      "max_score_ds": 63.8439,
      "receive_student_number": 10,
      "scores": {
        "gpax": 10,
        "tgat": 30,
        "a_lv_62": 15,
        "a_lv_70": 15,
        "a_lv_81": 15,
        "a_lv_82": 15
      }
    }
  ],
  "rounds": [
    {
      "_id": "68dcd01a4843519be397795c",
      "university_id": "004",
      "program_id": "10040119903201A",
      "project_id": "B1028",
      "project_name_th": "การรับนักกีฬาที่มีความสามารถดีเด่นระดับนานาชาติ/ระดับชาติ และนักกีฬาตามยุทธศาสตร์ (รหัส 00411901102010-การเมืองและการปกครอง)",
      "project_name_en": "",
      "join_id": "",
      "type": "1_2569",
      "receive_student_number": 2,
      "only_formal": 1,
      "only_international": 2,
      "only_vocational": 1,
      "only_non_formal": 1,
      "only_ged": 2,
      "description": "",
      "condition": "ตรวจสอบเกณฑ์การรับได้ที่นี่ https://admission.reg.cmu.ac.th/tcas/findfacultybyid.php?fid=64",
      "interview_location": "ขั้นตอนที่ต้องดำเนินการหลังประกาศผลการคัดเลือก https://cmu.to/tcas1",
      "interview_date": "",
      "interview_time": "",
      "link": "ผู้สมัครต้องตรวจสอบข้อมูลฉบับเต็มที่ https://admission.reg.cmu.ac.th/tcas/findfaculty.php",
      "grad_current": false,
      "t_score": false,
      "folio": {
        "closed_date": "",
        "page_limit": ""
      },
      "created_at": "2025-10-01T06:54:18.592Z",
      "score_conditions": {}
    },
    {
      "_id": "68dcd01a4843519be397795e",
      "university_id": "004",
      "program_id": "10040119903201A",
      "project_id": "E1019",
      "project_name_th": "การรับนักเรียนจากโครงการเด็กดีมีที่เรียน (รหัส 00411901105010-การเมืองและการปกครอง)",
      "project_name_en": "",
      "join_id": "",
      "type": "1_2569",
      "receive_student_number": 15,
      "only_formal": 1,
      "only_international": 2,
      "only_vocational": 2,
      "only_non_formal": 2,
      "only_ged": 2,
      "description": "",
      "condition": "ตรวจสอบเกณฑ์การรับได้ที่นี่ https://admission.reg.cmu.ac.th/tcas/findfacultybyid.php?fid=66",
      "interview_location": "ขั้นตอนที่ต้องดำเนินการหลังประกาศผลการคัดเลือก https://cmu.to/tcas1",
      "interview_date": "",
      "interview_time": "",
      "link": "ผู้สมัครต้องตรวจสอบข้อมูลฉบับเต็มที่ https://admission.reg.cmu.ac.th/tcas/findfaculty.php",
      "grad_current": false,
      "t_score": false,
      "folio": {
        "closed_date": "",
        "page_limit": ""
      },
      "created_at": "2025-10-01T06:54:18.597Z",
      "score_conditions": {}
    },
    {
      "_id": "68dcd01a4843519be3977960",
      "university_id": "004",
      "program_id": "10040119903201A",
      "project_id": "C1020",
      "project_name_th": "การรับนักเรียนที่มีผลการเรียนดี (รหัส 00411901103010-การเมืองและการปกครอง)",
      "project_name_en": "",
      "join_id": "",
      "type": "1_2569",
      "receive_student_number": 15,
      "only_formal": 1,
      "only_international": 2,
      "only_vocational": 2,
      "only_non_formal": 2,
      "only_ged": 2,
      "description": "",
      "condition": "ตรวจสอบเกณฑ์การรับได้ที่นี่ https://admission.reg.cmu.ac.th/tcas/findfacultybyid.php?fid=68",
      "interview_location": "ขั้นตอนที่ต้องดำเนินการหลังประกาศผลการคัดเลือก https://cmu.to/tcas1",
      "interview_date": "",
      "interview_time": "",
      "link": "ผู้สมัครต้องตรวจสอบข้อมูลฉบับเต็มที่ https://admission.reg.cmu.ac.th/tcas/findfaculty.php",
      "grad_current": false,
      "t_score": false,
      "folio": {
        "closed_date": "",
        "page_limit": ""
      },
      "created_at": "2025-10-01T06:54:18.603Z",
      "score_conditions": {}
    },
    {
      "_id": "68dcd01a4843519be3977962",
      "university_id": "004",
      "program_id": "10040119903201A",
      "project_id": "F1013",
      "project_name_th": "การรับนักเรียนพิการ (รหัส 00411901106010-การเมืองและการปกครอง)",
      "project_name_en": "",
      "join_id": "",
      "type": "1_2569",
      "receive_student_number": 1,
      "only_formal": 1,
      "only_international": 2,
      "only_vocational": 2,
      "only_non_formal": 2,
      "only_ged": 2,
      "description": "",
      "condition": "ตรวจสอบเกณฑ์การรับได้ที่นี่ https://admission.reg.cmu.ac.th/tcas/findfacultybyid.php?fid=75",
      "interview_location": "ขั้นตอนที่ต้องดำเนินการหลังประกาศผลการคัดเลือก https://cmu.to/tcas1",
      "interview_date": "",
      "interview_time": "",
      "link": "ผู้สมัครต้องตรวจสอบข้อมูลฉบับเต็มที่ https://admission.reg.cmu.ac.th/tcas/findfaculty.php",
      "grad_current": false,
      "t_score": false,
      "folio": {
        "closed_date": "",
        "page_limit": ""
      },
      "created_at": "2025-10-01T06:54:18.609Z",
      "score_conditions": {}
    },
    {
      "_id": "68dcd01a4843519be397797a",
      "university_id": "004",
      "program_id": "10040119903201A",
      "project_id": "H1146",
      "project_name_th": "โครงการพิเศษอื่นๆ โครงการ Change Agent (รหัส 00411901108010-การเมืองและการปกครอง)",
      "project_name_en": "",
      "join_id": "",
      "type": "1_2569",
      "receive_student_number": 3,
      "only_formal": 1,
      "only_international": 2,
      "only_vocational": 2,
      "only_non_formal": 2,
      "only_ged": 2,
      "description": "",
      "condition": "ตรวจสอบเกณฑ์การรับได้ที่นี่ https://admission.reg.cmu.ac.th/tcas/findfacultybyid.php?fid=1633",
      "interview_location": "ขั้นตอนที่ต้องดำเนินการหลังประกาศผลการคัดเลือก https://cmu.to/tcas1",
      "interview_date": "",
      "interview_time": "",
      "link": "ผู้สมัครต้องตรวจสอบข้อมูลฉบับเต็มที่ https://admission.reg.cmu.ac.th/tcas/findfaculty.php",
      "grad_current": false,
      "t_score": false,
      "folio": {
        "closed_date": "",
        "page_limit": ""
      },
      "created_at": "2025-10-01T06:54:18.679Z",
      "score_conditions": {}
    },
    {
      "_id": "68dcd01a4843519be3977984",
      "university_id": "004",
      "program_id": "10040119903201A",
      "project_id": "A1055",
      "project_name_th": "การรับด้วยแฟ้มสะสมผลงาน (รหัส 00411901101010-การเมืองและการปกครอง)",
      "project_name_en": "",
      "join_id": "",
      "type": "1_2569",
      "receive_student_number": 5,
      "only_formal": 1,
      "only_international": 1,
      "only_vocational": 2,
      "only_non_formal": 1,
      "only_ged": 1,
      "description": "",
      "condition": "ตรวจสอบเกณฑ์การรับได้ที่นี่ https://admission.reg.cmu.ac.th/tcas/findfacultybyid.php?fid=1265",
      "interview_location": "ขั้นตอนที่ต้องดำเนินการหลังประกาศผลการคัดเลือก https://cmu.to/tcas1",
      "interview_date": "",
      "interview_time": "",
      "link": "ผู้สมัครต้องตรวจสอบข้อมูลฉบับเต็มที่ https://admission.reg.cmu.ac.th/tcas/findfaculty.php",
      "grad_current": false,
      "t_score": false,
      "folio": {
        "closed_date": "",
        "page_limit": ""
      },
      "created_at": "2025-10-01T06:54:18.706Z",
      "score_conditions": {}
    },
    {
      "_id": "68dcd01d4843519be3977ccd",
      "university_id": "004",
      "program_id": "10040119903201A",
      "project_id": "I2015",
      "project_name_th": "การรับนักเรียนที่ดำเนินการโดยหน่วยงานอื่น โครงการจัดส่งนักศึกษาจังหวัดชายแดนภาคใต้เข้าศึกษาต่อมหาวิทยาลัย (รหัส 00421901211020-การเมืองและการปกครอง)",
      "project_name_en": "",
      "join_id": "",
      "type": "2_2569",
      "receive_student_number": 1,
      "only_formal": 1,
      "only_international": 2,
      "only_vocational": 2,
      "only_non_formal": 2,
      "only_ged": 2,
      "description": "",
      "condition": "ตรวจสอบเกณฑ์การรับได้ที่นี่ https://admission.reg.cmu.ac.th/tcas/findfacultybyid.php?fid=1275",
      "interview_location": "ขั้นตอนที่ต้องดำเนินการหลังประกาศผลการคัดเลือก https://cmu.to/tcas2",
      "interview_date": "",
      "interview_time": "",
      "link": "ผู้สมัครต้องตรวจสอบข้อมูลฉบับเต็มที่ https://admission.reg.cmu.ac.th/tcas/findfaculty.php",
      "grad_current": false,
      "t_score": false,
      "created_at": "2025-10-01T06:54:21.144Z",
      "score_conditions": {}
    },
    {
      "_id": "68dcd01d4843519be3977cd5",
      "university_id": "004",
      "program_id": "10040119903201A",
      "project_id": "J2145",
      "project_name_th": "การรับนักเรียนโควตาภาคเหนือฯ (รหัส 00421901201024-การเมืองและการปกครอง)",
      "project_name_en": "",
      "join_id": "",
      "type": "2_2569",
      "receive_student_number": 15,
      "only_formal": 1,
      "only_international": 2,
      "only_vocational": 2,
      "only_non_formal": 2,
      "only_ged": 2,
      "description": "",
      "condition": "ตรวจสอบเกณฑ์การรับได้ที่นี่ https://admission.reg.cmu.ac.th/tcas/findfacultybyid.php?fid=71",
      "interview_location": "ขั้นตอนที่ต้องดำเนินการหลังประกาศผลการคัดเลือก https://cmu.to/tcas2",
      "interview_date": "",
      "interview_time": "",
      "link": "ผู้สมัครต้องตรวจสอบข้อมูลฉบับเต็มที่ https://admission.reg.cmu.ac.th/tcas/findfaculty.php",
      "grad_current": false,
      "t_score": false,
      "created_at": "2025-10-01T06:54:21.165Z",
      "score_conditions": {}
    },
    {
      "_id": "68dcd01c4843519be3977c83",
      "university_id": "004",
      "program_id": "10040119903201A",
      "project_id": "L2013",
      "project_name_th": "การรับนักเรียนชาวไทยภูเขา (รหัส 00421901203013-การเมืองและการปกครอง)",
      "project_name_en": "",
      "join_id": "",
      "type": "2_2569",
      "receive_student_number": 1,
      "only_formal": 1,
      "only_international": 2,
      "only_vocational": 2,
      "only_non_formal": 2,
      "only_ged": 2,
      "description": "",
      "condition": "ตรวจสอบเกณฑ์การรับได้ที่นี่ https://admission.reg.cmu.ac.th/tcas/findfacultybyid.php?fid=73",
      "interview_location": "ขั้นตอนที่ต้องดำเนินการหลังประกาศผลการคัดเลือก https://cmu.to/tcas2",
      "interview_date": "",
      "interview_time": "",
      "link": "ผู้สมัครต้องตรวจสอบข้อมูลฉบับเต็มที่ https://admission.reg.cmu.ac.th/tcas/findfaculty.php",
      "grad_current": false,
      "t_score": false,
      "created_at": "2025-10-01T06:54:20.936Z",
      "score_conditions": {}
    },
    {
      "_id": "68dcd01c4843519be3977c7f",
      "university_id": "004",
      "program_id": "10040119903201A",
      "project_id": "J2144",
      "project_name_th": "การรับนักเรียนโควตาภาคเหนือฯ (รหัส 00421901201013-การเมืองและการปกครอง)",
      "project_name_en": "",
      "join_id": "",
      "type": "2_2569",
      "receive_student_number": 15,
      "only_formal": 1,
      "only_international": 2,
      "only_vocational": 2,
      "only_non_formal": 2,
      "only_ged": 2,
      "description": "",
      "condition": "ตรวจสอบเกณฑ์การรับได้ที่นี่ https://admission.reg.cmu.ac.th/tcas/findfacultybyid.php?fid=70",
      "interview_location": "ขั้นตอนที่ต้องดำเนินการหลังประกาศผลการคัดเลือก https://cmu.to/tcas2",
      "interview_date": "",
      "interview_time": "",
      "link": "ผู้สมัครต้องตรวจสอบข้อมูลฉบับเต็มที่ https://admission.reg.cmu.ac.th/tcas/findfaculty.php",
      "grad_current": false,
      "t_score": false,
      "created_at": "2025-10-01T06:54:20.925Z",
      "score_conditions": {}
    },
    {
      "_id": "68dcd01c4843519be3977c6f",
      "university_id": "004",
      "program_id": "10040119903201A",
      "project_id": "I2014",
      "project_name_th": "การรับนักเรียนที่ดำเนินการโดยหน่วยงานอื่น โครงการจัดส่งนักศึกษาจังหวัดชายแดนภาคใต้เข้าศึกษาต่อมหาวิทยาลัย (รหัส 00421901211010-การเมืองและการปกครอง)",
      "project_name_en": "",
      "join_id": "",
      "type": "2_2569",
      "receive_student_number": 1,
      "only_formal": 1,
      "only_international": 2,
      "only_vocational": 2,
      "only_non_formal": 2,
      "only_ged": 2,
      "description": "",
      "condition": "ตรวจสอบเกณฑ์การรับได้ที่นี่ https://admission.reg.cmu.ac.th/tcas/findfacultybyid.php?fid=1274",
      "interview_location": "ขั้นตอนที่ต้องดำเนินการหลังประกาศผลการคัดเลือก https://cmu.to/tcas2",
      "interview_date": "",
      "interview_time": "",
      "link": "ผู้สมัครต้องตรวจสอบข้อมูลฉบับเต็มที่ https://admission.reg.cmu.ac.th/tcas/findfaculty.php",
      "grad_current": false,
      "t_score": false,
      "created_at": "2025-10-01T06:54:20.891Z",
      "score_conditions": {}
    },
    {
      "_id": "68dcd01e4843519be3977f41",
      "university_id": "004",
      "program_id": "10040119903201A",
      "project_id": "M3157",
      "project_name_th": "การรับตรงร่วมกัน (รหัส 00431901301010-การเมืองและการปกครอง)",
      "project_name_en": "",
      "join_id": "",
      "type": "3_2569",
      "receive_student_number": 5,
      "only_formal": 1,
      "only_international": 2,
      "only_vocational": 2,
      "only_non_formal": 2,
      "only_ged": 2,
      "description": "",
      "condition": "ตรวจสอบเกณฑ์การรับได้ที่นี่ https://admission.reg.cmu.ac.th/tcas/findfacultybyid.php?fid=86",
      "interview_location": "ขั้นตอนที่ต้องดำเนินการหลังประกาศผลการคัดเลือก https://cmu.to/tcas3",
      "interview_date": "",
      "interview_time": "",
      "link": "ผู้สมัครต้องตรวจสอบข้อมูลฉบับเต็มที่ https://admission.reg.cmu.ac.th/tcas/findfaculty.php",
      "grad_current": false,
      "t_score": true,
      "min_gpax": 2.5,
      "score_conditions": {
        "min_gpax": 2.5,
        "min_a_lv_61_tscore": 45,
        "min_a_lv_70_tscore": 45,
        "min_a_lv_81_tscore": 45,
        "min_a_lv_82_tscore": 45
      },
      "created_at": "2025-10-01T06:54:22.896Z",
      "min_total_score": 0,
      "scores": {
        "gpax": 10,
        "tgat": 30,
        "a_lv_61": 15,
        "a_lv_70": 15,
        "a_lv_81": 15,
        "a_lv_82": 15
      }
    },
    {
      "_id": "68dcd01e4843519be3977f57",
      "university_id": "004",
      "program_id": "10040119903201A",
      "project_id": "M3158",
      "project_name_th": "การรับตรงร่วมกัน (รหัส 00431901301020-การเมืองและการปกครอง)",
      "project_name_en": "",
      "join_id": "",
      "type": "3_2569",
      "receive_student_number": 5,
      "only_formal": 1,
      "only_international": 2,
      "only_vocational": 2,
      "only_non_formal": 2,
      "only_ged": 2,
      "description": "",
      "condition": "ตรวจสอบเกณฑ์การรับได้ที่นี่ https://admission.reg.cmu.ac.th/tcas/findfacultybyid.php?fid=87",
      "interview_location": "ขั้นตอนที่ต้องดำเนินการหลังประกาศผลการคัดเลือก https://cmu.to/tcas3",
      "interview_date": "",
      "interview_time": "",
      "link": "ผู้สมัครต้องตรวจสอบข้อมูลฉบับเต็มที่ https://admission.reg.cmu.ac.th/tcas/findfaculty.php",
      "grad_current": false,
      "t_score": true,
      "min_gpax": 2.5,
      "score_conditions": {
        "min_gpax": 2.5,
        "min_a_lv_62_tscore": 45,
        "min_a_lv_70_tscore": 45,
        "min_a_lv_81_tscore": 45,
        "min_a_lv_82_tscore": 45
      },
      "created_at": "2025-10-01T06:54:22.955Z",
      "min_total_score": 0,
      "scores": {
        "gpax": 10,
        "tgat": 30,
        "a_lv_62": 15,
        "a_lv_70": 15,
        "a_lv_81": 15,
        "a_lv_82": 15
      }
    }
  ]
}