{
  "program": [
    {
      "program_id": "10360404702002A",
      "project_id": "A0408",
      "major_id": "0",
      "program_name_th": "หลักสูตรศึกษาศาสตรบัณฑิต สาขาวิชาการสอนภาษาอังกฤษ (4ปี)",
      "program_type_name_th": "ภาษาไทย ปกติ",
      "major_name_th": "0",
      "project_name_th": "หลักสูตรศึกษาศาสตรบัณฑิต สาขาวิชาการสอนภาษาอังกฤษ",
      "min_score": 84.25,
      "max_score": 84.25,
      "min_score_ds": 84.25,
      "max_score_ds": 84.25,
      "receive_student_number": 2,
      "scores": {
        "gpax": 100
      }
    }
  ],
  "rounds": [
    {
      "_id": "68f3513eaf9c8ecfd60c4872",
      "university_id": "036",
      "program_id": "10360404702002A",
      "project_id": "P0409",
      "project_name_th": "หลักสูตรศึกษาศาสตรบัณฑิต สาขาวิชาการสอนภาษาอังกฤษ",
      "project_name_en": "Bachelor of Education Program in Teaching English",
      "type": "1_2569",
      "receive_student_number": 25,
      "only_formal": 1,
      "only_international": 1,
      "only_vocational": 1,
      "only_non_formal": 1,
      "only_ged": 1,
      "description": "หลักสูตรศึกษาศาสตรบัณฑิต สาขาวิชาการสอนภาษาอังกฤษมุ่งผลิตบัณฑิตให้มีความรู้ความสามารถในด้านการสอนมีการบูรณาการการสอนให้เข้ากับวิชาการทางพระพุทธศาสนาสามารถปฏิบัติหน้าที่ความเป็นครูสอนภาษาอังกฤษและเป็นบัณฑิตมีความรู้ความสามารถ (Capability) ทางด้านการสอนภาษาอังกฤษกล้าคิด กล้าทำ กล้าวิพากษ์อย่างมีเหตุผล มีจรรยาบรรณและจริยธรรมสำหรับครูในการดำเนินชีวิตบนพื้นฐานหลักธรรมทางพระพุทธศาสนา\n  \n  จบแล้วทำอาชีพอะไร\n  ข้าราชการ/เจ้าพนักงานของรัฐ\n  ครูสอนภาษาอังกฤษ\n  บุคลากรทางการศึกษา\n  นักแปลภาษา/ล่าม\n  มัคคุเทศก์\n  ผู้ประกอบวิชาชีพที่ใช้ภาษาอังกฤษ\n  อาชีพส่วนตัวอื่น ๆ\n  1,9",
      "interview_location": "มหาวิทยาลัยมหามกุฏราชวิทยาลัย วิทยาเขตอีสาน 9/37 หมู่ 12 ต.ในเมือง อ.เมือง จ.ขอนแก่น รหัสไปรษณีย์ 40000 โทรศัพท์ 086-131-7448 หลังค่ายศรีพัชรินทร์ ใกล้บึงทุ่งสร้าง http://www.mbuisc.ac.th",
      "link": "https://mbuisc.ac.th/th/admission_mbuisc",
      "grad_current": false,
      "t_score": false,
      "min_gpax": 2,
      "score_conditions": {
        "min_gpax": 2
      },
      "folio": {
        "closed_date": "0",
        "page_limit": "0"
      },
      "created_at": "2025-10-18T08:35:10.042Z"
    },
    {
      "_id": "68f3513eaf9c8ecfd60c487a",
      "university_id": "036",
      "program_id": "10360404702002A",
      "project_id": "Q0409",
      "project_name_th": "หลักสูตรศึกษาศาสตรบัณฑิต สาขาวิชาการสอนภาษาอังกฤษ",
      "project_name_en": "Bachelor of Education Program in Teaching English",
      "type": "2_2569",
      "receive_student_number": 25,
      "only_formal": 1,
      "only_international": 1,
      "only_vocational": 1,
      "only_non_formal": 1,
      "only_ged": 1,
      "description": "หลักสูตรศึกษาศาสตรบัณฑิต สาขาวิชาการสอนภาษาอังกฤษมุ่งผลิตบัณฑิตให้มีความรู้ความสามารถในด้านการสอนมีการบูรณาการการสอนให้เข้ากับวิชาการทางพระพุทธศาสนาสามารถปฏิบัติหน้าที่ความเป็นครูสอนภาษาอังกฤษและเป็นบัณฑิตมีความรู้ความสามารถ (Capability) ทางด้านการสอนภาษาอังกฤษกล้าคิด กล้าทำ กล้าวิพากษ์อย่างมีเหตุผล มีจรรยาบรรณและจริยธรรมสำหรับครูในการดำเนินชีวิตบนพื้นฐานหลักธรรมทางพระพุทธศาสนา\n  จบแล้วทำอาชีพอะไร\n  ข้าราชการ/เจ้าพนักงานของรัฐ\n  ครูสอนภาษาอังกฤษ\n  บุคลากรทางการศึกษา\n  นักแปลภาษา/ล่าม\n  มัคคุเทศก์\n  ผู้ประกอบวิชาชีพที่ใช้ภาษาอังกฤษ\n  อาชีพส่วนตัวอื่น ๆ",
      "interview_location": "มหาวิทยาลัยมหามกุฏราชวิทยาลัย วิทยาเขตอีสาน 9/37 หมู่ 12 ต.ในเมือง อ.เมือง จ.ขอนแก่น รหัสไปรษณีย์ 40000 โทรศัพท์ 086-131-7448 หลังค่ายศรีพัชรินทร์ ใกล้บึงทุ่งสร้าง http://www.mbuisc.ac.th",
      "link": "https://mbuisc.ac.th/th/admission_mbuisc",
      "grad_current": false,
      "t_score": false,
      "min_gpax": 2,
      "score_conditions": {
        "min_gpax": 2
      },
      "created_at": "2025-10-18T08:35:10.066Z"
    },
    {
      "_id": "68f3513eaf9c8ecfd60c4882",
      "university_id": "036",
      "program_id": "10360404702002A",
      "project_id": "A0408",
      "project_name_th": "หลักสูตรศึกษาศาสตรบัณฑิต สาขาวิชาการสอนภาษาอังกฤษ",
      "project_name_en": "Bachelor of Education Program in Teaching English",
      "type": "3_2569",
      "receive_student_number": 5,
      "only_formal": 1,
      "only_international": 1,
      "only_vocational": 1,
      "only_non_formal": 1,
      "only_ged": 1,
      "description": "หลักสูตรศึกษาศาสตรบัณฑิต สาขาวิชาการสอนภาษาอังกฤษมุ่งผลิตบัณฑิตให้มีความรู้ความสามารถในด้านการสอนมีการบูรณาการการสอนให้เข้ากับวิชาการทางพระพุทธศาสนาสามารถปฏิบัติหน้าที่ความเป็นครูสอนภาษาอังกฤษและเป็นบัณฑิตมีความรู้ความสามารถ (Capability) ทางด้านการสอนภาษาอังกฤษกล้าคิด กล้าทำ กล้าวิพากษ์อย่างมีเหตุผล มีจรรยาบรรณและจริยธรรมสำหรับครูในการดำเนินชีวิตบนพื้นฐานหลักธรรมทางพระพุทธศาสนา\n  \n  จบแล้วทำอาชีพอะไร\n  ข้าราชการ/เจ้าพนักงานของรัฐ\n  ครูสอนภาษาอังกฤษ\n  บุคลากรทางการศึกษา\n  นักแปลภาษา/ล่าม\n  มัคคุเทศก์\n  ผู้ประกอบวิชาชีพที่ใช้ภาษาอังกฤษ\n  อาชีพส่วนตัวอื่น ๆ",
      "interview_location": "มหาวิทยาลัยมหามกุฏราชวิทยาลัย วิทยาเขตอีสาน 9/37 หมู่ 12 ต.ในเมือง อ.เมือง จ.ขอนแก่น รหัสไปรษณีย์ 40000 โทรศัพท์ 086-131-7448 หลังค่ายศรีพัชรินทร์ ใกล้บึงทุ่งสร้าง http://www.mbuisc.ac.th",
      "link": "https://mbuisc.ac.th/th/admission_mbuisc",
      "grad_current": false,
      "t_score": false,
      "min_gpax": 2,
      "score_conditions": {
        "min_gpax": 2
      },
      "created_at": "2025-10-18T08:35:10.099Z",
      "min_total_score": 0,
      "scores": {
        "gpax": 100
      }
    }
  ]
}